{"api_key":"20d7b3b4f8b62eaf716e4d20808d7da8","api_signature":"iI+a67uDVzSbUavrkWIFSeSbtpxxsIfGiH4nHaqJkckdA40iZ4RzAGnABbppbP5KRhEu8q/Y3l6fWhj6iWg+cCYSdQcYoYMi2g/nTGh5PsW/a9vATGGNqtuAxwghCNUzF8ZD3NxKTbKHCxp6mbfzxJi6FFkdA1RsCZCxx2gbTqY=","api_type":"Initiate","transaction_reference":"asdac23rsdc","transaction_status":"Completed","transaction_status_code":"200","transaction_status_description":"Success","transaction_account":"10001261","transaction_mobile":"250555555555","transaction_status_action":"go","transaction_country":"RW","transaction_amount":"0","transaction_method":"Paybill (Tigo Cash)","transaction_paybill":"961000","transaction_code":"213","transaction_date":"21/11/2020"},
